{
	"animations": [
		{
			"loop": true,
			"cameraOffset": [
				0,
				0
			],
			"offsets": [
				0,
				0
			],
			"anim": "idle",
			"fps": 24,
			"name": "idle",
			"indices": []
		},
		{
			"offsets": [
				58,
				-22
			],
			"indices": [],
			"fps": 24,
			"cameraOffset": [
				-30,
				0
			],
			"anim": "singLEFT",
			"loop": false,
			"name": "left"
		},
		{
			"offsets": [
				81,
				0
			],
			"indices": [],
			"fps": 24,
			"cameraOffset": [
				-30,
				0
			],
			"anim": "singLEFTmiss",
			"loop": false,
			"name": "missleft"
		},
		{
			"offsets": [
				15,
				-10
			],
			"indices": [],
			"fps": 24,
			"cameraOffset": [
				0,
				30
			],
			"anim": "singDOWN",
			"loop": false,
			"name": "down"
		},
		{
			"offsets": [
				19,
				48
			],
			"indices": [],
			"fps": 24,
			"cameraOffset": [
				0,
				30
			],
			"anim": "singDOWNmiss",
			"loop": false,
			"name": "missdown"
		},
		{
			"offsets": [
				-79,
				53
			],
			"indices": [],
			"fps": 24,
			"cameraOffset": [
				0,
				-30
			],
			"anim": "singUP",
			"loop": false,
			"name": "up"
		},
		{
			"offsets": [
				-21,
				59
			],
			"indices": [],
			"fps": 24,
			"cameraOffset": [
				0,
				-30
			],
			"anim": "singUPmiss",
			"loop": false,
			"name": "missup"
		},
		{
			"offsets": [
				1,
				11
			],
			"indices": [],
			"fps": 24,
			"cameraOffset": [
				30,
				0
			],
			"anim": "singRIGHT",
			"loop": false,
			"name": "right"
		},
		{
			"offsets": [
				34,
				49
			],
			"indices": [],
			"fps": 24,
			"cameraOffset": [
				30,
				0
			],
			"anim": "singRIGHTmiss",
			"loop": false,
			"name": "missright"
		}
	],
	"no_antialiasing": false,
	"image": "characters/boris",
	"position": [
		270,
		40
	],
	"healthicon": "boris",
	"flip_x": true,
	"healthbar_colors": [
		225,
		225,
		225
	],
	"camera_position": [
		0,
		0
	],
	"sing_duration": 4.00000000000001,
	"scale": 1
}